tests/__init__.py
tests/conftest.py
tests/test_analysis.py
tests/test_config_factory.py
tests/test_experiment.py
tests/test_grid.py
tests/test_plotter.py
tests/test_plotting.py
tests/test_trial.py
tests/test_tuneconfig.py
tuneconfig/__init__.py
tuneconfig/analysis.py
tuneconfig/config_factory.py
tuneconfig/experiment.py
tuneconfig/grid.py
tuneconfig/launcher.py
tuneconfig/plotter.py
tuneconfig/plotting.py
tuneconfig/trial.py
tuneconfig-0.14.1.dist-info/LICENSE
tuneconfig-0.14.1.dist-info/METADATA
tuneconfig-0.14.1.dist-info/WHEEL
tuneconfig-0.14.1.dist-info/top_level.txt
tuneconfig-0.14.1.dist-info/RECORD
